LICENSE
MANIFEST.in
README.rst
setup.py
django_pipeline_compass_rubygem.egg-info/PKG-INFO
django_pipeline_compass_rubygem.egg-info/SOURCES.txt
django_pipeline_compass_rubygem.egg-info/dependency_links.txt
django_pipeline_compass_rubygem.egg-info/not-zip-safe
django_pipeline_compass_rubygem.egg-info/top_level.txt
pipeline_compass/__init__.py
pipeline_compass/compass.py