Metadata-Version: 1.0
Name: django-pipeline-compass-rubygem
Version: 0.1.8
Summary: 
